{
    "header": {
        "logo": "logo.jpg",
        "links": [
            {
                "id": 0,
                "title": "Главный",
                "links": "/",
                "icon": "bi bi-chevron-down"
            },
            {
                "id": 1,
                "title": "О нас",
                "link": "#about",
                "icon": "bi bi-chevron-down"
            },
            {
                "id": 2,
                "title": "Страницы",
                "link": "#pages",
                "icon": "bi bi-chevron-down"
            },
            {
                "id": 3,
                "title": "Контакты",
                "link": "#contact",
                "icon": "bi bi-chevron-down"
            }
        ],
        "phone":"+998900078985"

    },
    "section1": {
        "title1": "Команда современных ИТ-специалистов с творческими способностями",
        "title2": "МЕЧТЫ СБЫВАЮТСЯ С НАМИ!",
        "title3": "МЫ ПРЕДОСТАВЛЯЕМ РЕАЛЬНЫЕ УРОКИ И УСЛУГИ ДЛЯ ПОДДЕРЖКИ ВАШЕГО УСПЕХА",
        "button": "УЗНАТЬ БОЛЬШЕ"
    },
    "section2": [
        {
            "img": "icon@15x.png",
            "title": "Стандарт",
            "sub_title": "обычный тип обучения, приемлемый для большинства. При этом занятия внеклассные – 3 дня в неделю по 2 часа"
        },
        {
            "img": "kTfOtgQDzjre.png",
            "title": "Интенсивный",
            "sub_title": "для тех, кто хочет быстро добиться результата. В данном виде обучения занятия проходят 6 дней в неделю по 4 часа. Кроме того, вы сможете самостоятельно устанавливать интенсивность уроков и учебных дней"
        },
        {
            "img": "2img@15x.png",
            "title": "Онлайн",
            "sub_title": "это форма обучения, которая позволяет учащимся с плотным графиком работы и учебы, которым неудобно посещать занятия, участвовать в наших занятиях и изучать IT в любом месте и в любое время. В этом случае вы сможете выбрать один из желаемых видов обучения – стандартное или интенсивное"
        },
        {
            "img": "4icon@15x.png",
            "title": "Оффлайн",
            "sub_title": "эта форма обучения позволяет оставаться с нами в нашей веселой атмосфере, проводить больше времени лицом к лицу с преподавателями и наставниками, а также пройти любой вид обучения - стандартный или интенсивный - в учебном центре Drenix academy"
        }
    ],
    "section3": {
        "title1": "КТО МЫ?",
        "title2": "Мы обучаем всех, кто интересуется такими областями, как программирование и дизайн и….",
        "title3": "Также мы специализируемся на цифровизации бизнеса в различных направлениях и помогаем им в дальнейшем развитии маркетинга.",
        "derektor": {
            "name": "Дурбек Рихсибоев",
            "job": "Главный директор",
            "company": "Drenix",
            "img": "derektor.jpg"
        },
        "adjus": [
            {
                "title": " Новое и современное образование"
            },
            {
                "title": " Работа в авторитетных организациях"
            },
            {
                "title": "Решение бизнес-задач"
            },
            {
                "title": "Гарантия надежного обслуживания"
            }
        ]
    },
    "section4": {
        "year": 5,
        "title1": "Опыт лет",
        "title2": "Мы предлагаем IT-курсы и услуги, которые гарантируют вам успех",
        "title3": "Выпускники нашего центра приобретают перечисленные навыки как полноценные специалисты своей профессии",
        "skills": [
            {
                "text": "Frontend",
                "value": 90
            },
            {
                "text": "Backend",
                "value": 85
            },
            {
                "text": "Javascript",
                "value": 90
            },
            {
                "text": "Графический дизайн",
                "value": 90
            },
            {
                "text": "Веб-дизайн",
                "value": 90
            },
            {
                "text": "React.js",
                "value": 80
            },
            {
                "text": "React Native",
                "value": 70
            },
            {
                "text": "Компьютерная грамотность",
                "value": 100
            }
        ],
        "courses": [
            {
                "text": "Frontend",
                "img": "x0LELqjTK6FC.jpg"
            },
            {
                "text": "Backend",
                "img": "2AMRb2Ws4zIY.jpeg"
            },
            {
                "text": "JavaScript",
                "img": "OfgD7rh4ZvN2.jpeg"
            },
            {
                "text": "Графический дизайн",
                "img": "x9bZh1JVxPOe.jpeg"
            }
        ],
        "fullSection": [
            {
                "value": 10,
                "icon": "+",
                "title": "реализованных проектов",
                "img": "bnLecUweEITo.png"
            },
            {
                "value": 30,
                "icon": "+",
                "title": "клиентов",
                "img": "uQWkoarAw2Ap.png"
            },
            {
                "value": 99,
                "icon": "%",
                "title": "анализ сайта",
                "img": "X2HOAP5USAjF.png"
            },
            {
                "value": 50,
                "icon": "+",
                "title": "отзывов клиентов",
                "img": "RydMvaGPfTrW.png"
            }
        ]
    },
    "sectoin5": {
        "title1": "Фотографии из жизни нашего центра",
        "title2": "У нас есть практические занятия на основе реальных проектов",
        "button": "",
        "corusel": [
            {
                "title": "",
                "img": "lavha1.jpg",
                "btn": "",
                "decr": ""
            },
            {
                "title": "",
                "img": "lavha2.jpg",
                "btn": "",
                "decr": ""
            },
            {
                "title": "",
                "img": "lavha3.jpg",
                "btn": "",
                "decr": ""
            }
        ]
    },
    "seaction6": {
        "title1": "ПОЧЕМУ МЫ?",
        "title2": "МЫ ПРЕДОСТАВЛЯЕМ КАЧЕСТВЕННЫЕ УРОКИ И УСЛУГИ, КОТОРЫЕ ГАРАНТИРУЮТ ВАМ УСПЕХ",
        "items": [
            {
                "title": "Команда экспертов",
                "decr": "Современные творческие IT-специалисты",
                "icon": "gRzLx7vhLY9k.png"
            },
            {
                "title": "Контроль качества",
                "decr": "Гарантируется, что уроки будут проводиться вовремя и на идеальном уровне.",
                "icon": "faTD9UvvWOUP.png"
            },
            {
                "title": "Интеграция",
                "decr": "Студенты нашего образовательного центра будут иметь возможность пользоваться услугами наших организаций-партнеров на льготных условиях во время обучения. Например, клиника «Себзор Мед Даво», маркетинговая команда « Drenix Marketing»",
                "icon": "qVn78YuXyXDo.png"
            },
            {
                "title": "Гарантированное трудоустройство",
                "decr": "Образовательный центр «Drenix academy» берет на себя ответственность за трудоустройство студентов на предприятия Узбекистана, предоставление им работы в качестве фрилансеров и даже найм их в собственную маркетинговую компанию после прохождения курса.",
                "icon": "RydMvaGPfTrW.png"
            }
        ]
    },
    "sectoin7": {
        "title1": "Наша команда",
        "title2": "Профессиональный персонал в области ИТ-технологий и технических областей",
        "team": [
            {
                "name": "Дурбек Риксибоев",
                "spes": "Главный директор",
                "img": "derektor.jpg",
                "facebook": {
                    "link": "#f",
                    "icon": "fa-brands fa-facebook"
                },
                "twitter": {
                    "link": "https://t.me/bek_dd/",
                    "icon": "fa-brands fa-telegram"
                },
                "youtube": {
                    "link": "https://instagram.com/rikhsiboevd/",
                    "icon": "fa-brands fa-instagram"
                }
            },
            {
                "name": "Мирали Норкулов",
                "spes": "",
                "img": "mirali.jpg",
                "facebook": {
                    "link": "#f",
                    "icon": "fa-brands fa-facebook"
                },
                "twitter": {
                    "link": "https://t.me/mirali_mansurovich",
                    "icon": "fa-brands fa-telegram"
                },
                "youtube": {
                    "link": "https://instagram.com/mirali_mansurovich/",
                    "icon": "fa-brands fa-instagram"
                }
            },
            {
                "name": "Акмаль Юлдашев",
                "spes": "CEO & Founder",
                "img": "akmal.jpg",
                "facebook": {
                    "link": "#f",
                    "icon": "fa-brands fa-facebook"
                },
                "twitter": {
                    "link": "https://t.me/@akmal_link/",
                    "icon": "fa-brands fa-telegram"
                },
                "youtube": {
                    "link": "https://instagram.com/_b_0_0_m/",
                    "icon": "fa-brands fa-instagram"
                }
            },
            {
                "name": "Диёрбек Юлдашов",
                "spes": "Full Stack Dasturchi",
                "img": "diyor.jpg",
                "facebook": {
                    "link": "https://www.facebook.com/by_diorr",
                    "icon": "fa-brands fa-facebook"
                },
                "twitter": {
                    "link": "https://t.me/by_diorr/",
                    "icon": "fa-brands fa-telegram"
                },
                "youtube": {
                    "link": "https://instagram.com/by_diorr/",
                    "icon": "fa-brands fa-instagram"
                }
            },
            {
                "name": "МирзоБабур Обиджонов",
                "spes": "CEO & Founder",
                "img": "bobur.jpg",
                "facebook": {
                    "link": "",
                    "icon": "fa-brands fa-facebook"
                },
                "twitter": {
                    "link": "",
                    "icon": "fa-brands fa-telegram"
                },
                "youtube": {
                    "link": "https://instagram.com/boburobidjonov0",
                    "icon": "fa-brands fa-instagram"
                }
            },
            {
                "name": "Фирдавс Шаропов",
                "spes": "Графический дизайнер",
                "img": "firdavs.jpg",
                "facebook": {
                    "link": "https://www.facebook.com/JamessRobets",
                    "icon": "fa-brands fa-facebook"
                },
                "twitter": {
                    "link": "https://t.me/warapovv/",
                    "icon": "fa-brands fa-telegram"
                },
                "youtube": {
                    "link": "https://instagram.com/_mukhammadjonovich_",
                    "icon": "fa-brands fa-instagram"
                }
            }
        ]
    },
    "section8": {
        "title1": "ПОЧЕМУ МЫ?",
        "title2": "Более 30+ клиентов довольны нашим сервисом и ИТ-решениями",
        "corusel": [
            {
                "first_title": "Fikrlar",
                "icon": "feedback5.png",
                "title": "'Drenix academy' o'quv markazi  faoliyati bilan avvaldan tanishman. Markazni yutuqlari, imkoniyatlari men uchun juda ma'qul bo'lgan edi. Shuning uchun ham men 'Sebzor Med Davo' klinikasining marketingini yuritishda 'Drenix academy' dan yordam so'radim. Markazning ustozlari, mentorlari, marketing guruh xodimlari, shuningdek, bitiruvchilari ham har sohada klinikamiz uchun yordam berganliklari uchun minnatdorchiligimni bildirib qolaman.",
                "name": "Gulbahor Isahonova ",
                "spec": "Sebzor Med Davo"
            },
            {
                "first_title": "Fikrlar",
                "icon": "feedback2.png",
                "title": "'Eco Freight Solution' logistik kompaniya yanayam yaxshi yurishi uchun 'Drenix academy'  juda ham qulay qilib sayt va bot yaratib berishdi. Buning uchun markazga ko'pdan ko'p rahmatimni aytaman.",
                "name": "Bahromoz Avazxon",
                "spec": "EFS direktori"
            },
            {
                "first_title": "Отзывы",
                "icon": "feedback6.png",
                "title": "Хорошая компания с качественным сервисом и достойными товарами. Несколько раз заказывал нестандартные и креативные зеркала и каждый раз удивлялся как они умело и точно воплощают в жизнь то, что я хочу. 10 из 10",
                "name": "WaffLessDay",
                "spec": ""
            },
            {
                "first_title": "Отзывы",
                "icon": "feedback3.png",
                "title": "Будучи примерной домохозяйкой я люблю приготовить вкусненькое. Поэтому мне нужна была хорошая сэндвич-панель. Скажу честно, купила и выбросила в мусор уже 3 штуки. И однажды вечером когда я уже начала расстраиваться мой муж обрадовал меня покупкой новой качественной сэндвич-панели от Pannel city. Пользуемся и наслаждаемся вкусными сэндвичами.",
                "name": " Pannel city",
                "spec": ""
            }
        ]
    },
    "section10": {
        "title1": "Станьте одним из наших счастливых клиентов",
        "corusel": [
            {
                "img": "hamkor1.jpg"
            },
            {
                "img": "hamkor2.jpg"
            },
            {
                "img": "hamkor3.jpg"
            },
            {
                "img": "hamkor4.jpg"
            },
            {
                "img": "hamkor5.jpg"
            }
        ],
        "contact": {
            "title1": "Быстрый контакт с нами",
            "phone": "+998900078985",
            "intName": [
                "Ваш номер телефона",
                "Имя пользователя Telegram"
            ],
            "label": "Ваш контакт",
            "place1": "Имя Фамилия",
            "place2": "Предложения и требования",
            "btn": "Отправить"
        }
    },
    "footer": {
        "useLink": [
            {
                "logo": {
                    "url": "logo",
                    "type": "logo.jpg"
                },
                "links": [
                    {
                        "icon": "fa-regular fa-phone",
                        "title": "+998900078985"
                    },
                    {
                        "icon": "fa-regular fa-envelope-open",
                        "title": "info@example.com"
                    },
                    {
                        "icon": "fa-regular fa-location-dot",
                        "title": "60 East 65th Street, NY"
                    }
                ]
            },
            {
                "logo": {
                    "url": "Полезные ссылки",
                    "type": "text"
                },
                "links": [
                    {
                        "url": "",
                        "title": "Условия"
                    },
                    {
                        "url": "",
                        "title": "О компании"
                    },
                    {
                        "url": "",
                        "title": "Платежный шлюз"
                    },
                    {
                        "url": "",
                        "title": "Политика конфиденциальности"
                    }
                ]
            },
            {
                "logo": {
                    "url": "Наши услуги",
                    "type": "text"
                },
                "links": [
                    {
                        "url": "",
                        "title": "Безопасность данных"
                    },
                    {
                        "url": "",
                        "title": "Управление ИТ"
                    },
                    {
                        "url": "",
                        "title": "SMM Сервисы"
                    },
                    {
                        "url": "",
                        "title": "Маркетинговые услуги"
                    }
                ]
            },
            {
                "logo": {
                    "url": "Поддерживать",
                    "type": "text"
                },
                "links": [
                    {
                        "url": "",
                        "title": "Документация"
                    },
                    {
                        "url": "",
                        "title": "Поддерживать"
                    },
                    {
                        "url": "",
                        "title": "Часто задаваемые вопросы"
                    },
                    {
                        "url": "",
                        "title": "Скачать"
                    }
                ]
            }
        ]
    }
}
